MANIFEST.in
setup.cfg
setup.py
test/test.py
xwot_dsl/__init__.py
xwot_dsl/grammarv05.py
xwot_dsl/helpers.py
xwot_dsl/messages.py
xwot_dsl/solver.py
xwot_dsl/xwot_dsl.py
xwot_dsl.egg-info/PKG-INFO
xwot_dsl.egg-info/SOURCES.txt
xwot_dsl.egg-info/dependency_links.txt
xwot_dsl.egg-info/requires.txt
xwot_dsl.egg-info/top_level.txt