Metadata-Version: 1.1
Name: xwot-dsl
Version: 1.0.9
Summary: xwot_dsl
Home-page: UNKNOWN
Author: Lars Voegtlin
Author-email: lvoegtlin@gmail.com
License: GPLv3
Platform: UNKNOWN
Classifier: License :: OSI Approved :: GNU General Public License v3 (GPLv3)
